LICENSE
MANIFEST.in
description.rst
readme.rst
setup.cfg
setup.py
django_postgres_extensions/__init__.py
django_postgres_extensions/apps.py
django_postgres_extensions/signals.py
django_postgres_extensions/utils.py
django_postgres_extensions/admin/__init__.py
django_postgres_extensions/admin/options.py
django_postgres_extensions/backends/__init__.py
django_postgres_extensions/backends/postgresql/__init__.py
django_postgres_extensions/backends/postgresql/base.py
django_postgres_extensions/backends/postgresql/creation.py
django_postgres_extensions/backends/postgresql/operations.py
django_postgres_extensions/backends/postgresql/schema.py
django_postgres_extensions/forms/__init__.py
django_postgres_extensions/forms/fields.py
django_postgres_extensions/forms/widgets.py
django_postgres_extensions/models/__init__.py
django_postgres_extensions/models/expressions.py
django_postgres_extensions/models/functions.py
django_postgres_extensions/models/lookups.py
django_postgres_extensions/models/query.py
django_postgres_extensions/models/fields/__init__.py
django_postgres_extensions/models/fields/related.py
django_postgres_extensions/models/fields/related_descriptors.py
django_postgres_extensions/models/fields/related_lookups.py
django_postgres_extensions/models/fields/reverse_related.py
django_postgres_extensions/models/sql/__init__.py
django_postgres_extensions/models/sql/compiler.py
django_postgres_extensions/models/sql/datastructures.py
django_postgres_extensions/models/sql/subqueries.py
django_postgres_extensions/models/sql/updates.py
django_postgres_extensions_compat.egg-info/PKG-INFO
django_postgres_extensions_compat.egg-info/SOURCES.txt
django_postgres_extensions_compat.egg-info/dependency_links.txt
django_postgres_extensions_compat.egg-info/top_level.txt